{
    "consumer": {
        "name": "sample-consumer"
    },
    "provider": {
        "name": "cds.category-experience-api"
    },
    "interactions": [
        {
            "description": "GET_/api/v1/categories/DC0000001_200 - Get Categories",
            "request": {
                "method": "GET",
                "path": "/api/v1/categories/DC0000001",
                "query": "",
                "headers": {
                    "Connection": "close",
                    "Accept": "application/json, text/plain, */*",
                    "baseSiteId": "CTR"
                }
            },
            "response": {
                "status": 200,
                "headers": {
                    "Connection": "close",
                    "Content-Type": "application/json"
                },
                "body": {
                    "id": "string",
                    "description": "string",
                    "url": [
                        {
                            "url": "string",
                            "hreflang": "string"
                        }
                    ],
                    "image": "string",
                    "subcategories": [
                        {
                            "id": "string",
                            "name": "string",
                            "url": "string",
                            "image": "string",
                            "searchLink": "string",
                            "isFitmentRequired": true,
                            "isRelatedCategory": true,
                            "subcategories": []
                        }
                    ],
                    "breadcrumbList": [
                        {
                            "label": "string",
                            "url": "string"
                        }
                    ],
                    "isFitmentRequired": true,
                    "noIndex": true,
                    "noFollow": true,
                    "productWheelType": "string",
                    "defaultView": "string",
                    "seoCopy": "string",
                    "seoTitle": "string",
                    "seoDescription": "string",
                    "canonicalUrl": "string",
                    "searchLink": "string"
                }
            },
            "timestamp": "2022-11-09T12:24:03.520Z"
        },
        {
            "description": "GET_/api/v1/categories_200 - Get the category tree for a provided identifier.",
            "request": {
                "method": "GET",
                "path": "/api/v1/categories",
                "query": "",
                "headers": {
                    "Connection": "close",
                    "Accept": "application/json, text/plain, */*",
                    "baseSiteId": "CTR"
                }
            },
            "response": {
                "status": 200,
                "headers": {
                    "Connection": "close",
                    "Content-Type": "application/json"
                },
                "body": {
                    "categories": [
                        {
                            "id": "string",
                            "name": "string",
                            "url": "string",
                            "searchLink": "string",
                            "image": "string",
                            "subcategories": []
                        }
                    ]
                }
            },
            "timestamp": "2022-11-09T12:24:03.814Z"
        },
        {
            "description": "GET_/health_200 - The health status of the service",
            "request": {
                "method": "GET",
                "path": "/health",
                "query": "",
                "headers": {
                    "Connection": "close",
                    "Accept": "application/json, text/plain, */*"
                }
            },
            "response": {
                "status": 200,
                "headers": {
                    "Connection": "close",
                    "Content-Type": "application/json"
                },
                "body": {
                    "name": "category_api_microservice",
                    "status": "OK",
                    "message": "Service is up and running.",
                    "build": "1.0.0",
                    "uptime": 0
                }
            },
            "timestamp": "2022-11-09T12:24:04.034Z"
        },
        {
            "description": "GET_/health_500 - The health status of the service",
            "request": {
                "method": "GET",
                "path": "/health",
                "query": "",
                "headers": {
                    "Connection": "close"
                }
            },
            "response": {
                "status": 500,
                "headers": {
                    "Connection": "close"
                }
            },
            "timestamp": "2022-11-09T12:24:05.064Z"
        }
    ],
    "metadata": {
        "pactSpecification": {
            "version": "2.0.0"
        },
        "client": {
            "name": "pact-mountebank-adapter",
            "version": "1.0.10"
        }
    }
}